pysqlutil/__init__.py
pysqlutil/compat.py
pysqlutil/generalizator.py
pysqlutil/keywords_lists.py
pysqlutil/parser.py
pysqlutil/token.py
pysqlutil/utils.py
pysqlutil-1.0.1.dist-info/LICENSE
pysqlutil-1.0.1.dist-info/METADATA
pysqlutil-1.0.1.dist-info/WHEEL
pysqlutil-1.0.1.dist-info/top_level.txt
pysqlutil-1.0.1.dist-info/RECORD
