Metadata-Version: 2.1
Name: pysqlutil
Version: 1.0.1
Summary: parse sql , compare two .sql file , generate optimization hint for your sql and various other utilities
Home-page: https://github.com/koustreak/dot.parser
Author: Koushik Dutta <a.k.a DotPY>
Author-email: dot.py@yahoo.com
License: MIT
Platform: UNKNOWN
Classifier: License :: OSI Approved :: MIT License
Classifier: Programming Language :: Python
Classifier: Programming Language :: Python :: 3
Classifier: Programming Language :: Python :: 3.10
Classifier: Programming Language :: Python :: Implementation :: CPython
Classifier: Programming Language :: Python :: Implementation :: PyPy
Requires-Python: >=3.9.0
License-File: LICENSE
Requires-Dist: pip (==22.3.1)
Requires-Dist: setuptools (==65.5.0)
Requires-Dist: sqlparse (==0.4.3)
Requires-Dist: wheel (==0.37.1)
